orca_whirlpool/__init__.py
orca_whirlpool/accounts.py
orca_whirlpool/constants.py
orca_whirlpool/context.py
orca_whirlpool/instruction.py
orca_whirlpool/quote.py
orca_whirlpool/transaction.py
orca_whirlpool/types.py
orca_whirlpool/utils.py
orca_whirlpool/internal/__init__.py
orca_whirlpool/internal/constants.py
orca_whirlpool/internal/context.py
orca_whirlpool/internal/errors.py
orca_whirlpool/internal/invariant.py
orca_whirlpool/internal/accounts/__init__.py
orca_whirlpool/internal/accounts/account_fetcher.py
orca_whirlpool/internal/accounts/account_finder.py
orca_whirlpool/internal/accounts/account_parser.py
orca_whirlpool/internal/accounts/keyed_account_converter.py
orca_whirlpool/internal/accounts/types.py
orca_whirlpool/internal/anchor/__init__.py
orca_whirlpool/internal/anchor/program_id.py
orca_whirlpool/internal/anchor/accounts/__init__.py
orca_whirlpool/internal/anchor/accounts/fee_tier.py
orca_whirlpool/internal/anchor/accounts/position.py
orca_whirlpool/internal/anchor/accounts/position_bundle.py
orca_whirlpool/internal/anchor/accounts/tick_array.py
orca_whirlpool/internal/anchor/accounts/token_badge.py
orca_whirlpool/internal/anchor/accounts/whirlpool.py
orca_whirlpool/internal/anchor/accounts/whirlpools_config.py
orca_whirlpool/internal/anchor/accounts/whirlpools_config_extension.py
orca_whirlpool/internal/anchor/errors/__init__.py
orca_whirlpool/internal/anchor/errors/anchor.py
orca_whirlpool/internal/anchor/errors/custom.py
orca_whirlpool/internal/anchor/instructions/__init__.py
orca_whirlpool/internal/anchor/instructions/close_bundled_position.py
orca_whirlpool/internal/anchor/instructions/close_position.py
orca_whirlpool/internal/anchor/instructions/close_position_with_token_extensions.py
orca_whirlpool/internal/anchor/instructions/collect_fees.py
orca_whirlpool/internal/anchor/instructions/collect_fees_v2.py
orca_whirlpool/internal/anchor/instructions/collect_protocol_fees.py
orca_whirlpool/internal/anchor/instructions/collect_protocol_fees_v2.py
whirlpool_essentials-0.1.0.dist-info/METADATA
whirlpool_essentials-0.1.0.dist-info/WHEEL
whirlpool_essentials-0.1.0.dist-info/licenses/LICENSE
whirlpool_essentials-0.1.0.dist-info/RECORD
