Metadata-Version: 2.4
Name: whirlpool-essentials
Version: 0.1.0
Summary: A core library to interact with Orca Whirlpool
Project-URL: Homepage, https://github.com/everlastingsong/whirlpool-essentials
Project-URL: Documentation, https://everlastingsong.github.io/whirlpool-essentials/orca_whirlpool/index.html
Project-URL: Issues, https://github.com/everlastingsong/whirlpool-essentials/issues
Author-email: yugure <yugure@orca.so>
License-File: LICENSE
Classifier: License :: OSI Approved :: MIT License
Classifier: Operating System :: OS Independent
Classifier: Programming Language :: Python :: 3
Requires-Python: >=3.10
